backends/__init__.py
backends/mlx_backend.py
recursive_cleaner/__init__.py
recursive_cleaner/cleaner.py
recursive_cleaner/context.py
recursive_cleaner/dependencies.py
recursive_cleaner/errors.py
recursive_cleaner/metrics.py
recursive_cleaner/optimizer.py
recursive_cleaner/output.py
recursive_cleaner/parser_generator.py
recursive_cleaner/parsers.py
recursive_cleaner/prompt.py
recursive_cleaner/report.py
recursive_cleaner/response.py
recursive_cleaner/schema.py
recursive_cleaner/tui.py
recursive_cleaner/types.py
recursive_cleaner/validation.py
recursive_cleaner/vendor/__init__.py
recursive_cleaner/vendor/chunker.py
recursive_cleaner-0.8.0.dist-info/METADATA
recursive_cleaner-0.8.0.dist-info/WHEEL
recursive_cleaner-0.8.0.dist-info/licenses/LICENSE
recursive_cleaner-0.8.0.dist-info/RECORD
