Metadata-Version: 2.4
Name: recursive-cleaner
Version: 0.8.0
Summary: LLM-powered incremental data cleaning pipeline that processes massive datasets in chunks and generates Python cleaning functions
Project-URL: Homepage, https://github.com/gaztrabisme/recursive-data-cleaner
Project-URL: Repository, https://github.com/gaztrabisme/recursive-data-cleaner
Project-URL: Issues, https://github.com/gaztrabisme/recursive-data-cleaner/issues
Author: Gary Tran
License-Expression: MIT
License-File: LICENSE
Keywords: automation,data-cleaning,data-quality,etl,llm,machine-learning
Classifier: Development Status :: 4 - Beta
Classifier: Intended Audience :: Developers
Classifier: Intended Audience :: Science/Research
Classifier: License :: OSI Approved :: MIT License
Classifier: Operating System :: OS Independent
Classifier: Programming Language :: Python :: 3
Classifier: Programming Language :: Python :: 3.10
Classifier: Programming Language :: Python :: 3.11
Classifier: Programming Language :: Python :: 3.12
Classifier: Topic :: Scientific/Engineering :: Artificial Intelligence
Classifier: Topic :: Text Processing :: General
Classifier: Topic :: Utilities
Requires-Python: >=3.10
Requires-Dist: tenacity>=8.0
Provides-Extra: dev
Requires-Dist: pytest-cov>=4.0; extra == 'dev'
Requires-Dist: pytest>=7.0; extra == 'dev'
Provides-Extra: markitdown
Requires-Dist: markitdown>=0.1.0; extra == 'markitdown'
Provides-Extra: mlx
Requires-Dist: mlx-lm>=0.10.0; extra == 'mlx'
Provides-Extra: parquet
Requires-Dist: pyarrow>=14.0.0; extra == 'parquet'
Provides-Extra: tui
Requires-Dist: rich>=13.0; extra == 'tui'
